odoo/addons/ssi_risk_analysis_project/README.rst
odoo/addons/ssi_risk_analysis_project/__init__.py
odoo/addons/ssi_risk_analysis_project/__manifest__.py
odoo/addons/ssi_risk_analysis_project/models/__init__.py
odoo/addons/ssi_risk_analysis_project/models/risk_analysis.py
odoo/addons/ssi_risk_analysis_project/models/risk_analysis_worksheet.py
odoo/addons/ssi_risk_analysis_project/static/description/icon.png
odoo14_addon_ssi_risk_analysis_project-14.0.1.0.0.dist-info/METADATA
odoo14_addon_ssi_risk_analysis_project-14.0.1.0.0.dist-info/WHEEL
odoo14_addon_ssi_risk_analysis_project-14.0.1.0.0.dist-info/top_level.txt
odoo14_addon_ssi_risk_analysis_project-14.0.1.0.0.dist-info/RECORD
